yirgacheffe/__init__.py
yirgacheffe/_core.py
yirgacheffe/constants.py
yirgacheffe/operators.py
yirgacheffe/py.typed
yirgacheffe/window.py
yirgacheffe/_backends/__init__.py
yirgacheffe/_backends/enumeration.py
yirgacheffe/_backends/mlx.py
yirgacheffe/_backends/numpy.py
yirgacheffe/_datatypes/__init__.py
yirgacheffe/_datatypes/area.py
yirgacheffe/_datatypes/mapprojection.py
yirgacheffe/_datatypes/pixelscale.py
yirgacheffe/_datatypes/window.py
yirgacheffe/_operators/__init__.py
yirgacheffe/_operators/cse.py
yirgacheffe/layers/__init__.py
yirgacheffe/layers/area.py
yirgacheffe/layers/base.py
yirgacheffe/layers/constant.py
yirgacheffe/layers/group.py
yirgacheffe/layers/h3layer.py
yirgacheffe/layers/rasters.py
yirgacheffe/layers/rescaled.py
yirgacheffe/layers/vectors.py
yirgacheffe-1.11.3.dist-info/licenses/LICENSE
yirgacheffe-1.11.3.dist-info/METADATA
yirgacheffe-1.11.3.dist-info/WHEEL
yirgacheffe-1.11.3.dist-info/entry_points.txt
yirgacheffe-1.11.3.dist-info/top_level.txt
yirgacheffe-1.11.3.dist-info/RECORD
