Metadata-Version: 2.4
Name: yirgacheffe
Version: 1.11.3
Summary: Abstraction of gdal datasets for doing basic math operations
Author-email: Michael Dales <mwd24@cam.ac.uk>
License-Expression: ISC
Project-URL: Homepage, https://yirgacheffe.org/
Project-URL: Repository, https://github.com/quantifyearth/yirgacheffe.git
Project-URL: Issues, https://github.com/quantifyearth/yirgacheffe/issues
Project-URL: Changelog, https://yirgacheffe.org/latest/changelog/
Keywords: gdal,gis,geospatial,declarative
Classifier: Development Status :: 5 - Production/Stable
Classifier: Intended Audience :: Science/Research
Classifier: Programming Language :: Python :: 3
Classifier: Programming Language :: Python :: 3.10
Classifier: Programming Language :: Python :: 3.11
Classifier: Programming Language :: Python :: 3.12
Classifier: Topic :: Scientific/Engineering :: GIS
Requires-Python: >=3.10
License-File: LICENSE
Requires-Dist: numpy<3.0,>=1.24
Requires-Dist: gdal[numpy]<4.0,>=3.8
Requires-Dist: scikit-image<1.0,>=0.20
Requires-Dist: torch
Requires-Dist: dill
Requires-Dist: deprecation
Requires-Dist: tomli
Requires-Dist: h3
Requires-Dist: pyproj
Provides-Extra: mlx
Requires-Dist: mlx; extra == "mlx"
Provides-Extra: matplotlib
Requires-Dist: matplotlib; extra == "matplotlib"
Provides-Extra: dev
Requires-Dist: mypy; extra == "dev"
Requires-Dist: pylint; extra == "dev"
Requires-Dist: pytest; extra == "dev"
Requires-Dist: pytest-cov; extra == "dev"
Requires-Dist: pytest-mock; extra == "dev"
Requires-Dist: build; extra == "dev"
Requires-Dist: twine; extra == "dev"
Requires-Dist: mkdocs-material; extra == "dev"
Requires-Dist: mkdocstrings-python; extra == "dev"
Requires-Dist: mike; extra == "dev"
Requires-Dist: mkdocs-gen-files; extra == "dev"
Requires-Dist: black; extra == "dev"
Dynamic: license-file
